spotrpy/__init__.py
spotrpy/commands.py
spotrpy/main.py
spotrpy/api/API.py
spotrpy/api/__init__.py
spotrpy/assets/LOGO.py
spotrpy/assets/__init__.py
spotrpy/config/__init__.py
spotrpy/config/config.py
spotrpy/controllers/__init__.py
spotrpy/controllers/artistController.py
spotrpy/controllers/asciiController.py
spotrpy/controllers/authController.py
spotrpy/controllers/currentController.py
spotrpy/controllers/nextController.py
spotrpy/controllers/playbackController.py
spotrpy/controllers/playlistController.py
spotrpy/controllers/playlistaddController.py
spotrpy/controllers/previousController.py
spotrpy/controllers/qsearchController.py
spotrpy/controllers/queueController.py
spotrpy/controllers/recentController.py
spotrpy/controllers/recommendController.py
spotrpy/controllers/replayController.py
spotrpy/controllers/searchController.py
spotrpy/controllers/seekController.py
spotrpy/controllers/shuffleController.py
spotrpy/controllers/startController.py
spotrpy/controllers/stopController.py
spotrpy/controllers/volumeController.py
spotrpy/controllers/webController.py
spotrpy/core/BaseController.py
spotrpy/core/__init__.py
spotrpy/interface/Command.py
spotrpy/interface/__init__.py
spotrpy/logging/Logging.py
spotrpy/logging/__init__.py
spotrpy/parser/__init__.py
spotrpy/parser/parser.py
spotrpy/util/ASCII.py
spotrpy/util/Helpers.py
spotrpy/util/__init__.py
spotrpy-4.1.dist-info/LICENSE.md
spotrpy-4.1.dist-info/METADATA
spotrpy-4.1.dist-info/WHEEL
spotrpy-4.1.dist-info/entry_points.txt
spotrpy-4.1.dist-info/top_level.txt
spotrpy-4.1.dist-info/RECORD
