Metadata-Version: 2.1
Name: spotrpy
Version: 4.1
Summary: A simple spotify tool for the terminal
Home-page: https://github.com/Havard03/spotr
Author: Havard03
Author-email: havard.buvang@gmail.com
Keywords: cli
Classifier: Programming Language :: Python :: 3
Classifier: License :: OSI Approved :: MIT License
Classifier: Operating System :: OS Independent
Requires-Python: >=3.6
License-File: LICENSE.md
Requires-Dist: Pillow==10.1.0
Requires-Dist: questionary==2.0.1
Requires-Dist: requests==2.28.1
Requires-Dist: rich==13.6.0
Requires-Dist: tqdm==4.66.1
